SicpInPython/README.md
SicpInPython/__init__.py
SicpInPython/__main__.py
SicpInPython/file.epub
SicpInPython/index.html
SicpInPython/css/__init__.py
SicpInPython/css/annotations.css
SicpInPython/css/main.css
SicpInPython/css/normalize.css
SicpInPython/css/popup.css
SicpInPython/font/__init__.py
SicpInPython/font/fontello.eot
SicpInPython/font/fontello.svg
SicpInPython/font/fontello.ttf
SicpInPython/font/fontello.woff
SicpInPython/img/__init__.py
SicpInPython/img/annotator-glyph-sprite.png
SicpInPython/img/annotator-icon-sprite.png
SicpInPython/img/apple-touch-icon.png
SicpInPython/img/cancelfullscreen.png
SicpInPython/img/close.png
SicpInPython/img/fullscreen.png
SicpInPython/img/loader.gif
SicpInPython/img/menu-icon.png
SicpInPython/img/save.png
SicpInPython/img/saved.png
SicpInPython/img/settings-s.png
SicpInPython/img/settings.png
SicpInPython/img/star.png
SicpInPython/js/__init__.py
SicpInPython/js/epub.js
SicpInPython/js/epub.min.js
SicpInPython/js/epub.min.map
SicpInPython/js/hooks.min.js
SicpInPython/js/hooks.min.map
SicpInPython/js/reader.js
SicpInPython/js/reader.js.map
SicpInPython/js/reader.min.js
SicpInPython/js/reader.min.map
SicpInPython/js/hooks/__init__.py
SicpInPython/js/hooks/extensions/__init__.py
SicpInPython/js/hooks/extensions/highlight.js
SicpInPython/js/libs/__init__.py
SicpInPython/js/libs/jquery.min.js
SicpInPython/js/libs/localforage.min.js
SicpInPython/js/libs/screenfull.js
SicpInPython/js/libs/screenfull.min.js
SicpInPython/js/libs/zip.min.js
SicpInPython/js/plugins/__init__.py
SicpInPython/js/plugins/hypothesis.js
SicpInPython/js/plugins/search.js
sicp_in_python-2024.3.2.0.dist-info/METADATA
sicp_in_python-2024.3.2.0.dist-info/WHEEL
sicp_in_python-2024.3.2.0.dist-info/entry_points.txt
sicp_in_python-2024.3.2.0.dist-info/top_level.txt
sicp_in_python-2024.3.2.0.dist-info/RECORD
